kermit_sdr/__init__.py
kermit_sdr/collect_data.py
kermit_sdr/config.py
kermit_sdr/generate_map.py
kermit_sdr/kermit.py
kermit_sdr/sample_signal_distribution.py
kermit_sdr/utils.py
kermit_sdr/version.py
kermit_sdr-0.1.1.dist-info/LICENSE
kermit_sdr-0.1.1.dist-info/METADATA
kermit_sdr-0.1.1.dist-info/WHEEL
kermit_sdr-0.1.1.dist-info/entry_points.txt
kermit_sdr-0.1.1.dist-info/top_level.txt
kermit_sdr-0.1.1.dist-info/RECORD
