Metadata-Version: 2.1
Name: kermit-sdr
Version: 0.1.1
Summary: UNKNOWN
Home-page: https://github.com/benhg/kermit
Author: Benjamin Glick
Author-email: glick@glick.cloud
License: MIT
Keywords: kermit,radio,SDR,map,geospatial
Platform: UNKNOWN
Classifier: Development Status :: 3 - Alpha
Classifier: Intended Audience :: Science/Research
Classifier: License :: OSI Approved :: Apache Software License
Classifier: Natural Language :: English
Classifier: Operating System :: OS Independent
Classifier: Programming Language :: Python :: 3
Classifier: Topic :: Scientific/Engineering
Requires-Python: >=3.6.0
License-File: LICENSE
Requires-Dist: pyrtlsdr
Requires-Dist: numpy
Requires-Dist: scipy
Requires-Dist: pyserial
Requires-Dist: pandas
Requires-Dist: plotly
